composer/__init__.py
composer/py.typed
class_composer-0.1.0.dist-info/LICENSE
class_composer-0.1.0.dist-info/WHEEL
class_composer-0.1.0.dist-info/METADATA
class_composer-0.1.0.dist-info/RECORD
