Metadata-Version: 2.1
Name: class-composer
Version: 0.1.0
Summary: A library for making dataclasses
License: MIT
Author: andy
Author-email: andy.development@protonmail.com
Requires-Python: >=3.9,<4.0
Classifier: License :: OSI Approved :: MIT License
Classifier: Programming Language :: Python :: 3
Classifier: Programming Language :: Python :: 3.10
Classifier: Programming Language :: Python :: 3.9
Requires-Dist: typing-extensions (>=4.1.1,<5.0.0)
